institMove/__init__.py
institMove/cmfIndicatorPkg.py
institMove/institMovePgk.py
institMove-0.0.2.dist-info/LICENSE
institMove-0.0.2.dist-info/METADATA
institMove-0.0.2.dist-info/WHEEL
institMove-0.0.2.dist-info/top_level.txt
institMove-0.0.2.dist-info/RECORD
