Metadata-Version: 2.1
Name: institMove
Version: 0.0.2
Summary: cmf indicator with specific grouping
Home-page: https://github.com/pstrito/cmfWebAppPip.git
Author: Example Author
Author-email: author@example.com
License: UNKNOWN
Platform: UNKNOWN
Classifier: Programming Language :: Python :: 3
Classifier: License :: OSI Approved :: MIT License
Classifier: Operating System :: OS Independent
License-File: LICENSE
